Workbook
Name CIQWBGuid: "e778162b-a8f3-4f2e-935f-34d73fb7e972"
Name CIQWBGuid: "eeeac8b3-2cb4-40c8-a5e7-67bd1e29d27d"
Name CIQWBInfo: "{ ""CIQVersion"":""9.51.3510.3078"" }"
Name CurrentPrice: #REF!
Name Gross_Profit: '[1]Advanced Financial Analysis'!$9:$9
Name IFF_Price: #REF!
Name IQ_CH: 110000
Name IQ_CQ: 5000
Name IQ_CY: 10000
Name IQ_DAILY: 500000
Name IQ_DNTM: 700000
Name IQ_FH: 100000
Name IQ_FQ: 500
Name IQ_FWD_CY: 10001
Name IQ_FWD_CY1: 10002
Name IQ_FWD_CY2: 10003
Name IQ_FWD_FY: 1001
Name IQ_FWD_FY1: 1002
Name IQ_FWD_FY2: 1003
Name IQ_FWD_Q: 501
Name IQ_FWD_Q1: 502
Name IQ_FWD_Q2: 503
Name IQ_FY: 1000
Name IQ_LATESTK: 1000
Name IQ_LATESTQ: 500
Name IQ_LTM: 2000
Name IQ_LTMMONTH: 120000
Name IQ_MONTH: 15000
Name IQ_MTD: 800000
Name IQ_NAMES_REVISION_DATE_: 45318.8008796296
Name IQ_NTM: 6000
Name IQ_QTD: 750000
Name IQ_TODAY: 0
Name IQ_WEEK: 50000
Name IQ_YTD: 3000
Name IQ_YTDMONTH: 130000
Name Sensitivity: '[1]Advanced Financial Analysis'!$D$49
Name SG_A: '[1]Advanced Financial Analysis'!$11:$11
Name TargetCurrentPrice: #REF!
Name TargetDilutedShares: #REF!

Sheet Assumptions
C2: First Solar
C3: Assumptions
C4: Active Case: | D4: 1
C6: £ In Millions, Unless Otherwise Noted
F7: Historical Years | I7: Forecasted Years
F8: 2021A | G8: 2022A | H8: 2023A | I8: 2024A | J8: 2025A | K8: 2026E | L8: 2027E | M8: 2028E
C10: Products Revenue | F10: ='Three Statement Model'!D31 -> 8.3 | G10: ='Three Statement Model'!E31 -> 8.2 | H10: ='Three Statement Model'!F31 -> 30.5 | I10: ='Three Statement Model'!G31 -> 11.9 | J10: ='Three Statement Model'!H31 -> 78 | K10: 102.2 | L10: 123 | M10: 130.38
C11: % Growth | G11: =(G10-F10)/F10 -> -0.012048193 | H11: =(H10-G10)/G10 -> 2.7195122 | I11: =(I10-H10)/H10 -> -0.60983607 | J11: =(J10-I10)/I10 -> 5.5546218 | K11: =(K10-J10)/J10 -> 0.31025641 | L11: =(L10-K10)/K10 -> 0.2035225 | M11: =(M10-L10)/L10 -> 0.06 | N11: 2026 forecast based on H1 revenue of 51.1m and guidance of continued strenght
C14: Cost of Goods Sold | F14: =-'Three Statement Model'!D32 -> 5.1 | G14: =-'Three Statement Model'!E32 -> 5.5 | H14: =-'Three Statement Model'!F32 -> 19.5 | I14: =-'Three Statement Model'!G32 -> 8.5 | J14: =-'Three Statement Model'!H32 -> 54.1 | K14: =K10*(K15) -> 68.985 | L14: =L10*(L15) -> 79.95 | M14: =M10*(M15) -> 84.747
C15: % of Products Revenue | F15: =F14/F10 -> 0.61445783 | G15: =G14/G10 -> 0.67073171 | H15: =H14/H10 -> 0.63934426 | I15: ='Three Statement Model'!G32/'Three Statement Model'!G31*-1 -> 0.71428571 | J15: ='Three Statement Model'!H32/'Three Statement Model'!H31*-1 -> 0.69358974 | K15: =+OFFSET(K15,$D$4,) -> 0.675 | L15: =+OFFSET(L15,$D$4,) -> 0.65 | M15: =+OFFSET(M15,$D$4,) -> 0.65
C16: Base | K16: 0.675 | L16: 0.65 | M16: 0.65
C17: Bull | K17: 0.6 | L17: 0.6 | M17: 0.6
C18: Bear | K18: 0.7 | L18: 0.7 | M18: 0.7
C20: SG&A Expense | F20: ='Three Statement Model'!D35 -> 5.8 | G20: ='Three Statement Model'!E35 -> 6.5 | H20: ='Three Statement Model'!F35 -> 8.3 | I20: ='Three Statement Model'!G35 -> 11.3 | J20: ='Three Statement Model'!H35 -> 14.8 | K20: =K21*(K10) -> 20.44 | L20: =L21*(L10) -> 21.525 | M20: =M21*(M10) -> 19.557
C21: % of Revenue | F21: =F20/F10 -> 0.69879518 | G21: =G20/G10 -> 0.79268293 | H21: =H20/H10 -> 0.27213115 | I21: =I20/I10 -> 0.94957983 | J21: =J20/J10 -> 0.18974359 | K21: =+OFFSET(K21,$D$4,) -> 0.2 | L21: =+OFFSET(L21,$D$4,) -> 0.175 | M21: =+OFFSET(M21,$D$4,) -> 0.15
C22: Base | K22: 0.2 | L22: 0.175 | M22: 0.15
C23: Bull | K23: 0.15 | L23: 0.125 | M23: 0.1
C24: Bear | K24: 0.2 | L24: 0.2 | M24: 0.2
C27: Depreciation & Amort | F27: ='Three Statement Model'!D106 -> 0.5 | G27: ='Three Statement Model'!E106 -> 0.5 | H27: ='Three Statement Model'!F106 -> 0.5 | I27: ='Three Statement Model'!G106 -> 0.4 | J27: ='Three Statement Model'!H106 -> 0.5 | K27: =K28*K10 -> 0.6132 | L27: =L28*L10 -> 0.738 | M27: =M28*M10 -> 0.78228
C28: % of Revenue | F28: =F27/F10 -> 0.060240964 | G28: =G27/G10 -> 0.06097561 | H28: =H27/H10 -> 0.016393443 | I28: =I27/I10 -> 0.033613445 | J28: =J27/J10 -> 0.0064102564 | K28: =+OFFSET(K28,$D$4,) -> 0.006 | L28: =+OFFSET(L28,$D$4,) -> 0.006 | M28: =+OFFSET(M28,$D$4,) -> 0.006
C29: Base | K29: 0.006 | L29: 0.006 | M29: 0.006
C30: Bull | K30: 0.004 | L30: 0.004 | M30: 0.004
C31: Bear | K31: 0.01 | L31: 0.01 | M31: 0.01
C33: Other Operating Expense | F33: ='Three Statement Model'!D38 -> 0 | G33: ='Three Statement Model'!E38 -> 0 | H33: ='Three Statement Model'!F38 -> 0 | I33: ='Three Statement Model'!G38 -> 0 | J33: ='Three Statement Model'!H38 -> 0 | K33: =K34*K10 -> 0 | L33: =L34*L10 -> 0 | M33: =M34*M10 -> 0
C34: % of Revenue | F34: =F33/(F10) -> 0 | G34: =G33/(G10) -> 0 | H34: =H33/(H10) -> 0 | I34: =I33/(I10) -> 0 | J34: =J33/(J10) -> 0 | K34: =+OFFSET(K34,$D$4,) -> 0 | L34: =+OFFSET(L34,$D$4,) -> 0 | M34: =+OFFSET(M34,$D$4,) -> 0
C35: Base | K35: 0 | L35: 0 | M35: 0
C36: Bull | K36: 0 | L36: 0 | M36: 0
C37: Bear | K37: 0.005 | L37: 0.005 | M37: 0.005
C39: Other Non-Operating Inc. | F39: =-'Three Statement Model'!D49 -> 0 | G39: =-'Three Statement Model'!E49 -> 0 | H39: =-'Three Statement Model'!F49 -> 0 | I39: =-'Three Statement Model'!G49 -> 0 | J39: =-'Three Statement Model'!H49 -> -3.4 | K39: =K40*K10 -> 0 | L39: =L40*L10 -> 0 | M39: =M40*M10 -> 0
C40: % of Revenue | F40: =F39/(F10) -> 0 | G40: =G39/(G10) -> 0 | H40: =H39/(H10) -> 0 | I40: =I39/(I10) -> 0 | J40: =J39/(J10) -> -0.043589744 | K40: =+OFFSET(K40,$D$4,) -> 0 | L40: =+OFFSET(L40,$D$4,) -> 0 | M40: =+OFFSET(M40,$D$4,) -> 0
C41: Base | K41: 0 | L41: 0 | M41: 0
C42: Bull | K42: 0 | L42: 0 | M42: 0
C43: Bear | K43: 0 | L43: 0 | M43: 0
C45: Accounts Receivable | F45: ='Three Statement Model'!D64 -> 2.3 | G45: ='Three Statement Model'!E64 -> 1.7 | H45: ='Three Statement Model'!F64 -> 3.3 | I45: ='Three Statement Model'!G64 -> 2.1 | J45: ='Three Statement Model'!H64 -> 50.8 | K45: =(K46*K10/365) -> 56 | L45: =(L46*L10/365) -> 67.39726 | M45: =(M46*M10/365) -> 71.441096
C46: Accounts Receivable Days | F46: =(F45/(F10))*365 -> 101.14458 | G46: =(G45/(G10))*365 -> 75.670732 | H46: =(H45/(H10))*365 -> 39.491803 | I46: =(I45/(I10))*365 -> 64.411765 | J46: =(J45/(J10))*365 -> 237.71795 | K46: =+OFFSET(K46,$D$4,) -> 200 | L46: =+OFFSET(L46,$D$4,) -> 200 | M46: =+OFFSET(M46,$D$4,) -> 200
C47: Base | K47: 200 | L47: 200 | M47: 200
C48: Bull | K48: 250 | L48: 250 | M48: 250
C49: Bear | K49: 175 | L49: 175 | M49: 150
C52: Long-Term Investments | F52: ='Three Statement Model'!D75 -> 9 | G52: ='Three Statement Model'!E75 -> 9.3 | H52: ='Three Statement Model'!F75 -> 11.7 | I52: ='Three Statement Model'!G75 -> 14.1 | J52: ='Three Statement Model'!H75 -> 16.7 | K52: =(K10*K53) -> 15.33 | L52: =(L10*L53) -> 15.375 | M52: =(M10*M53) -> 13.038
C53: % of Revenue | F53: =F52/(F10) -> 1.0843373 | G53: =G52/(G10) -> 1.1341463 | H53: =H52/(H10) -> 0.38360656 | I53: =I52/(I10) -> 1.1848739 | J53: =J52/(J10) -> 0.21410256 | K53: =+OFFSET(K53,$D$4,) -> 0.15 | L53: =+OFFSET(L53,$D$4,) -> 0.125 | M53: =+OFFSET(M53,$D$4,) -> 0.1
C54: Base | K54: 0.15 | L54: 0.125 | M54: 0.1
C55: Bull | K55: 0.175 | L55: 0.15 | M55: 0.15
C56: Bear | K56: 0.125 | L56: 0.1 | M56: 0.075
C58: Accounts Payable | F58: ='Three Statement Model'!D79 -> 1 | G58: ='Three Statement Model'!E79 -> 1.5 | H58: ='Three Statement Model'!F79 -> 2.5 | I58: ='Three Statement Model'!G79 -> 2.4 | J58: ='Three Statement Model'!H79 -> 5.2 | K58: =K59*K10/365 -> 8.4 | L58: =L59*L10/365 -> 10.109589 | M58: =M59*M10/365 -> 10.716164
C59: Accounts Payable Days | F59: =(F58/(F10))*365 -> 43.975904 | G59: =(G58/(G10))*365 -> 66.768293 | H59: =(H58/(H10))*365 -> 29.918033 | I59: =(I58/(I10))*365 -> 73.613445 | J59: =(J58/(J10))*365 -> 24.333333 | K59: =+OFFSET(K59,$D$4,) -> 30 | L59: =+OFFSET(L59,$D$4,) -> 30 | M59: =+OFFSET(M59,$D$4,) -> 30
C60: Base | K60: 30 | L60: 30 | M60: 30
C61: Bull | K61: 40 | L61: 40 | M61: 40
C62: Bear | K62: 20 | L62: 20 | M62: 20
C64: Capital Expenditures | F64: =-'Three Statement Model'!D117 -> 0.3 | G64: =-'Three Statement Model'!E117 -> 0.2 | H64: =-'Three Statement Model'!F117 -> 0.2 | I64: =-'Three Statement Model'!G117 -> 0.2 | J64: =-'Three Statement Model'!H117 -> 0.5 | K64: =K10*K65 -> 1.533 | L64: =L10*L65 -> 1.845 | M64: =M10*M65 -> 1.9557
C65: % of Revenue | F65: =F64/F10 -> 0.036144578 | G65: =G64/G10 -> 0.024390244 | H65: =H64/H10 -> 0.006557377 | I65: =I64/I10 -> 0.016806723 | J65: =J64/J10 -> 0.0064102564 | K65: =+OFFSET(K65,$D$4,) -> 0.015 | L65: =+OFFSET(L65,$D$4,) -> 0.015 | M65: =+OFFSET(M65,$D$4,) -> 0.015
C66: Base | K66: 0.015 | L66: 0.015 | M66: 0.015
C67: Bull | K67: 0.01 | L67: 0.01 | M67: 0.01
C68: Bear | K68: 0.02 | L68: 0.02 | M68: 0.02
C70: Purchase of Intangible Assets + Product Development | F70: 2.8 | G70: 3.3 | H70: 4.8 | I70: 4.6 | J70: 4.4 | K70: =K10*K71 -> 5.11 | L70: =L10*L71 -> 6.15 | M70: =M10*M71 -> 6.519
C71: % of Revenue | F71: =F70/F10 -> 0.3373494 | G71: =G70/G10 -> 0.40243902 | H71: =H70/H10 -> 0.15737705 | I71: =I70/I10 -> 0.38655462 | J71: =J70/J10 -> 0.056410256 | K71: =+OFFSET(K71,$D$4,) -> 0.05 | L71: =+OFFSET(L71,$D$4,) -> 0.05 | M71: =+OFFSET(M71,$D$4,) -> 0.05
C72: Base | K72: 0.05 | L72: 0.05 | M72: 0.05
C73: Bull | K73: 0.08 | L73: 0.08 | M73: 0.08
C74: Bear | K74: 0.03 | L74: 0.03 | M74: 0.03
C76: Tax Rate | F76: ='Three Statement Model'!D52/'Three Statement Model'!D47 -> 0.13333333 | G76: ='Three Statement Model'!E52/'Three Statement Model'!E47 -> 0.14925373 | H76: ='Three Statement Model'!F52/'Three Statement Model'!F47 -> 1 | I76: ='Three Statement Model'!G52/'Three Statement Model'!G47 -> 0.051724138 | J76: ='Three Statement Model'!H52/'Three Statement Model'!H47 -> -0.125 | K76: =+OFFSET(K76,$D$4,) -> 0.13 | L76: =+OFFSET(L76,$D$4,) -> 0.15 | M76: =+OFFSET(M76,$D$4,) -> 0.16
C77: Base | K77: 0.13 | L77: 0.15 | M77: 0.16
C78: Bull | K78: 0.12 | L78: 0.14 | M78: 0.15
C79: Bear | K79: 0.14 | L79: 0.16 | M79: 0.18
C81: Other Current Liabilities | F81: ='Three Statement Model'!D80+'Three Statement Model'!D82 -> 0.6 | I81: =I82*H14 -> 1.2675 | J81: =J82*I14 -> 0.5525 | K81: =K82*J14 -> 5.951 | L81: =L82*K14 -> 7.58835 | M81: =M82*L14 -> 8.7945
C82: % of COGS | F82: =F81/F14 -> 0.11764706 | G82: =G81/G14 -> 0 | H82: =H81/H14 -> 0 | I82: =I81/I14 -> 0.11764706 | J82: =J81/J14 -> 0.11764706 | K82: =+OFFSET(K82,$D$4,) -> 0.11 | L82: =+OFFSET(L82,$D$4,) -> 0.11 | M82: =+OFFSET(M82,$D$4,) -> 0.11
C83: Base | K83: 0.11 | L83: 0.11 | M83: 0.11
C84: Bull | K84: 0.06 | L84: 0.06 | M84: 0.06
C85: Bear | K85: 0.14 | L85: 0.14 | M85: 0.14
C87: Current Portion of Leases | F87: ='Three Statement Model'!D81 -> 8.8 | I87: =I88*H14 -> 0 | J87: =J88*I14 -> 0 | K87: =K88*J14 -> 0 | L87: =L88*K14 -> 0 | M87: =M88*L14 -> 0
C88: % of COGS | F88: =F87/H14 -> 0.45128205 | G88: =G87/I14 -> 0 | H88: =H87/J14 -> 0 | I88: =I87/I14 -> 0 | J88: =J87/J14 -> 0 | K88: =+OFFSET(K88,$D$4,) -> 0 | L88: =+OFFSET(L88,$D$4,) -> 0 | M88: =+OFFSET(M88,$D$4,) -> 0
C89: Base | K89: 0 | L89: 0 | M89: 0
C90: Bull | K90: 0 | L90: 0 | M90: 0
C91: Bear | K91: 0.0005 | L91: 0.0005 | M91: 0.0005
C93: Interest Expense | F93: =-'Three Statement Model'!D43 -> 0.6 | G93: =-'Three Statement Model'!E43 -> 0.6 | H93: =-'Three Statement Model'!F43 -> 0.8 | I93: =-'Three Statement Model'!G43 -> 1 | J93: =-'Three Statement Model'!H43 -> 1.9 | K93: =K94*J14 -> 0.67625 | L93: =L94*K14 -> 0.8623125 | M93: =M94*L14 -> 0.999375
C94: %Revenue | F94: =F93/H10 -> 0.019672131 | G94: =G93/I10 -> 0.050420168 | H94: =H93/J10 -> 0.01025641 | I94: =I93/K10 -> 0.0097847358 | J94: =J93/L10 -> 0.015447154 | K94: =+OFFSET(K94,$D$4,) -> 0.0125 | L94: =+OFFSET(L94,$D$4,) -> 0.0125 | M94: =+OFFSET(M94,$D$4,) -> 0.0125
C95: Base | K95: 0.0125 | L95: 0.0125 | M95: 0.0125
C96: Bull | K96: 0.008 | L96: 0.008 | M96: 0.008
C97: Bear | K97: 0.015 | L97: 0.015 | M97: 0.015
C99: Share Sales | F99: ='Three Statement Model'!D129 -> 2 | G99: ='Three Statement Model'!E129 -> 4.9 | H99: ='Three Statement Model'!F129 -> 0.1 | I99: ='Three Statement Model'!G129 -> 12.8 | J99: ='Three Statement Model'!H129 -> 9.5 | K99: =H10*K100 -> 3.05 | L99: =I10*L100 -> 0.8925 | M99: =J10*M100 -> 3.9
C100: % of Revenue | F100: =F99/F10 -> 0.24096386 | G100: =G99/G10 -> 0.59756098 | H100: =H99/H10 -> 0.0032786885 | I100: =I99/I10 -> 1.0756303 | J100: =J99/J10 -> 0.12179487 | K100: =+OFFSET(K100,$D$4,) -> 0.1 | L100: =+OFFSET(L100,$D$4,) -> 0.075 | M100: =+OFFSET(M100,$D$4,) -> 0.05
C101: Base | K101: 0.1 | L101: 0.075 | M101: 0.05
C102: Bull | K102: 0.05 | L102: 0.03 | M102: 0.015
C103: Bear | K103: 0.12 | L103: 0.1 | M103: 0.08

Sheet Metrics & Drivers
B2: Metrics & Drivers | G2: Case
B3: $ in millions, unless otherwise noted | G3: =#REF! -> #REF!
B5: For Fiscal Year Ending | F5: 2021 | G5: =F5+1 -> 2022 | H5: =G5+1 -> 2023 | I5: =H5+1 -> 2024 | J5: =I5+1 -> 2025 | K5: =J5+1 -> 2026 | L5: =K5+1 -> 2027 | M5: =L5+1 -> 2028
A7: x | B7: Revenue Build
B9: Revenue
B10: % of revenue | I10: =OFFSET(I37,$G$3,0)
B11: Base
B12: Bull
B13: Bear
B15: Modules Sold per year
B16: % Growth | I16: =OFFSET(I37,$G$3,0)
B17: Base
B18: Bull
B19: Bear
A34: x | B34: Other Metrics & Drivers
B36: Cost of Goods Sold
B37: % of revenue | I37: =OFFSET(I37,$G$3,0)
B38: Base
B39: Bull
B40: Bear
B42: SG&A Expense
B43: % of revenue
B44: Base
B45: Bull
B46: Bear
B48: D&A Expense
B49: % of capex
B50: Base
B51: Bull
... B130: Bear

Sheet Additional Schedules
B2: Additional Schedules
B3: $ in millions, unless otherwise noted
B5: For Fiscal Year Ending | F5: 2021 | G5: =F5+1 -> 2022 | H5: =G5+1 -> 2023 | I5: =H5+1 -> 2024 | J5: =I5+1 -> 2025 | K5: =J5+1 -> 2026 | L5: =K5+1 -> 2027 | M5: =L5+1 -> 2028
B7: Net Working Capital
B9: Current Operating Asset 1
B10: Current Operating Asset 2
B11: Current Operating Asset 3
B12: Current Operating Asset 4
B13: Total Current Operating Assets
B15: Current Operating Liability 1
B16: Current Operating Liability 2
B17: Current Operating Liability 3
B18: Current Operating Liability 4
B19: Total Current Operating Liabilities
B21: Net Working Capital
B22: Change in Net Working Capital

Sheet Three Statement Model
B5: Assumptions & Drivers
B7: All figures in USD Millions unless stated | D7: 2021A | E7: 2022A | F7: 2023A | G7: 2024A | H7: 2025A | I7: 2026E | J7: 2027E | K7: 2028E
B9: Days in Period | D9: 365 | E9: 365 | F9: 365 | G9: =365+1 -> 366 | H9: 365 | I9: 365 | J9: 365 | K9: =365+1 -> 366
B11: Income Statement
B12: Sales Growth | E12: =E31/D31-1 -> -0.012048193 | F12: =F31/E31-1 -> 2.7195122 | G12: =G31/F31-1 -> -0.60983607 | H12: =H31/G31-1 -> 5.5546218 | I12: =Assumptions!K11 -> 0.31025641 | J12: =Assumptions!L11 -> 0.2035225 | K12: =Assumptions!M11 -> 0.06
B13: Gross Margin | D13: =D33/D31 -> 0.38554217 | E13: =E33/E31 -> 0.32926829 | F13: =F33/F31 -> 0.36065574 | G13: =G33/G31 -> 0.28571429 | H13: =H33/H31 -> 0.30641026 | I13: =(1-Assumptions!K15) -> 0.325 | J13: =(1-Assumptions!L15) -> 0.35 | K13: =(1-Assumptions!M15) -> 0.35
B14: SG&A | D14: =D35 -> 5.8 | E14: =E35 -> 6.5 | F14: =F35 -> 8.3 | G14: =G35 -> 11.3 | H14: =H35 -> 14.8 | I14: =Assumptions!K21*Assumptions!K10 -> 20.44 | J14: =Assumptions!L21*Assumptions!L10 -> 21.525 | K14: =Assumptions!M21*Assumptions!M10 -> 19.557
B15: Capital Expenditure % of Revenue | D15: =D117/D31*-1 -> 0.036144578 | E15: =E117/E31*-1 -> 0.024390244 | F15: =F117/F31*-1 -> 0.006557377 | G15: =G117/G31*-1 -> 0.016806723 | H15: =H117/H31*-1 -> 0.0064102564 | I15: =Assumptions!K65 -> 0.015 | J15: =Assumptions!L65 -> 0.015 | K15: =Assumptions!M65 -> 0.015
B16: Interest Expense % of Revenue | D16: =D43/D31 -> -0.072289157 | E16: =E43/E31 -> -0.073170732 | F16: =F43/F31 -> -0.026229508 | G16: =G43/G31 -> -0.084033613 | H16: =H43/H31 -> -0.024358974 | I16: =-Assumptions!K94 -> -0.0125 | J16: =-Assumptions!L94 -> -0.0125 | K16: =-Assumptions!M94 -> -0.0125
B17: Depreciation (Percent of Sales) | D17: =D106/D31 -> 0.060240964 | E17: =E106/E31 -> 0.06097561 | F17: =F106/F31 -> 0.016393443 | G17: =G106/G31 -> 0.033613445 | H17: =H106/H31 -> 0.0064102564 | I17: =Assumptions!K28 -> 0.006 | J17: =Assumptions!L28 -> 0.006 | K17: =Assumptions!M28 -> 0.006
B18: Tax Rate (Percent of EBT) | D18: =D52/D47*-1 -> -0.13333333 | E18: =E52/E47*-1 -> -0.14925373 | F18: =F52/F47*-1 -> -1 | G18: =G52/G47*-1 -> -0.051724138 | H18: =H52/H47*-1 -> 0.125 | I18: =Assumptions!K76 -> 0.13 | J18: =Assumptions!L76 -> 0.15 | K18: =Assumptions!M76 -> 0.16
B20: Balance Sheet
B21: Capital Asset Turnover Ratio | C21: (x) | D21: =D31/D73 -> 4.8823529 | E21: =E31/E73 -> 6.3076923 | F21: =F31/F73 -> 25.416667 | G21: =G31/G73 -> 10.818182 | H21: =H31/H73 -> 55.714286 | I21: =I31/I73 -> 67.771883 | J21: =J31/J73 -> 76.012261 | K21: =K31/K73 -> 75.341377
B22: Receivable Days (Sales Basis) | C22: (Days) | D22: =Assumptions!F46 -> 101.14458 | E22: =Assumptions!G46 -> 75.670732 | F22: =Assumptions!H46 -> 39.491803 | G22: =Assumptions!I46 -> 64.411765 | H22: =Assumptions!J46 -> 237.71795 | I22: =Assumptions!K46 -> 200 | J22: =Assumptions!L46 -> 200 | K22: =Assumptions!M46 -> 200
B23: Inventory Days (COGS Basis) | C23: (Days) | D23: =D65/-D32*D9 -> 171.76471 | E23: =E65/-E32*E9 -> 159.27273 | F23: =F65/-F32*F9 -> 65.512821 | G23: =G65/-G32*G9 -> 348.77647 | H23: =H65/-H32*H9 -> 27.661738 | I23: =I65/-I32*I9 -> 26.455026 | J23: =J65/-J32*J9 -> 22.826767 | K23: =K65/-K32*K9 -> 21.593685
B24: Payable Days (COGS Basis) | C24: (Days) | D24: =Assumptions!F59 -> 43.975904 | E24: =Assumptions!G59 -> 66.768293 | F24: =Assumptions!H59 -> 29.918033 | G24: =Assumptions!I59 -> 73.613445 | H24: =Assumptions!J59 -> 24.333333 | I24: =Assumptions!K59 -> 30 | J24: =Assumptions!L59 -> 30 | K24: =Assumptions!M59 -> 30
B25: Long Term Debt | D25: =D86 -> 0 | E25: =E86 -> 0.3 | F25: =F86 -> 0 | G25: =G86 -> 3 | H25: =H86 -> 3 | I25: =I86 -> 3 | J25: =J86 -> 3 | K25: =K86 -> 3
B27: Income Statement
B29: All figures in USD Millions unless stated | D29: =D$7 -> 2021A | E29: =E$7 -> 2022A | F29: =F$7 -> 2023A | G29: =G$7 -> 2024A | H29: =H$7 -> 2025A | I29: =I$7 -> 2026E | J29: =J$7 -> 2027E | K29: =K$7 -> 2028E
B31: Total Revenue | D31: 8.3 | E31: 8.2 | F31: 30.5 | G31: 11.9 | H31: 78 | I31: =H31*(1+I12) -> 102.2 | J31: =I31*(1+J12) -> 123 | K31: =J31*(1+K12) -> 130.38
B32: Cost Of Goods Sold | D32: -5.1 | E32: -5.5 | F32: -19.5 | G32: -8.5 | H32: -54.1 | I32: =-Assumptions!K14 -> -68.985 | J32: =-Assumptions!L14 -> -79.95 | K32: =-Assumptions!M14 -> -84.747
B33: Gross Profit | D33: =SUM(D31,D32) -> 3.2 | E33: =SUM(E31,E32) -> 2.7 | F33: =SUM(F31,F32) -> 11 | G33: =SUM(G31,G32) -> 3.4 | H33: =SUM(H31,H32) -> 23.9 | I33: =SUM(I31,I32) -> 33.215 | J33: =SUM(J31,J32) -> 43.05 | K33: =SUM(K31,K32) -> 45.633
B35: Selling General & Admin Exp. | D35: 5.8 | E35: 6.5 | F35: 8.3 | G35: 11.3 | H35: 14.8 | I35: =Assumptions!K20 -> 20.44 | J35: =Assumptions!L20 -> 21.525 | K35: =Assumptions!M20 -> 19.557
B36: Depreciation & Amort. | D36: 0 | E36: 0 | F36: 0 | G36: 0 | H36: 0 | I36: =Assumptions!K27 -> 0.6132 | J36: =Assumptions!L27 -> 0.738 | K36: =Assumptions!M27 -> 0.78228
B37: Amort. Of Goodwill and Intangibles | D37: 2.3 | E37: 2.2 | F37: 2.4 | G37: 2.7 | H37: 2.7 | I37: 3 | J37: 3.3 | K37: 3.6 | L37: Increase in line with capitalized development expenditure
B38: Other Operating Expenses | D38: 0 | E38: 0 | F38: 0 | G38: 0 | H38: 0 | I38: 0 | J38: 0 | K38: 0 | L38: flatline
B39: Total Operating Expenses | D39: =SUM(D35:D38) -> 8.1 | E39: =SUM(E35:E38) -> 8.7 | F39: =SUM(F35:F38) -> 10.7 | G39: =SUM(G35:G38) -> 14 | H39: =SUM(H35:H38) -> 17.5 | I39: =SUM(I35:I38) -> 24.0532 | J39: =SUM(J35:J38) -> 25.563 | K39: =SUM(K35:K38) -> 23.93928
B41: EBIT (Operating Income) | D41: =D33-D39 -> -4.9 | E41: =E33-E39 -> -6 | F41: =F33-F39 -> 0.3 | G41: =G33-G39 -> -10.6 | H41: =H33-H39 -> 6.4 | I41: =I33-I39 -> 9.1618 | J41: =J33-J39 -> 17.487 | K41: =K33-K39 -> 21.69372
B43: Interest Expense | D43: -0.6 | E43: -0.6 | F43: -0.8 | G43: -1 | H43: -1.9 | I43: =Assumptions!K93 -> 0.67625 | J43: =Assumptions!L93 -> 0.8623125 | K43: =Assumptions!M93 -> 0.999375
B44: Interest and Invest. Income | D44: 0 | E44: 0 | F44: 0 | G44: 0 | H44: 0.3 | I44: 0.3 | J44: 0.3 | K44: 0.3 | L44: flatline
B45: Foreign Currency Loss | D45: -0.5 | E45: -0.1 | F45: -0.2 | G45: 0 | H45: 0 | I45: 0 | J45: 0 | K45: 0 | L45: flatline
B46: Net Interest Exp. | D46: =SUM(D43:D45) -> -1.1 | E46: =SUM(E43:E45) -> -0.7 | F46: =SUM(F43:F45) -> -1 | G46: =SUM(G43:G45) -> -1 | H46: =SUM(H43:H45) -> -1.6 | I46: =-Assumptions!K93 -> -0.67625 | J46: =-Assumptions!L93 -> -0.8623125 | K46: =-Assumptions!M93 -> -0.999375
B47: Earnings Before Taxes | D47: =D41+D46 -> -6 | E47: =E41+E46 -> -6.7 | F47: =F41+F46 -> -0.7 | G47: =G41+G46 -> -11.6 | H47: =H41+H46 -> 4.8 | I47: =I41+I46 -> 8.48555 | J47: =J41+J46 -> 16.624687 | K47: =K41+K46 -> 20.694345
B49: Non-operating Income Expense | D49: 0 | E49: 0 | F49: 0 | G49: 0 | H49: 3.4 | I49: 0 | J49: 0 | K49: 0
B50: EBT Including Unusual Items | D50: =D47-D49 -> -6 | E50: =E47-E49 -> -6.7 | F50: =F47-F49 -> -0.7 | G50: =G47-G49 -> -11.6 | H50: =H47-H49 -> 1.4 | I50: =I47-I49 -> 8.48555 | J50: =J47-J49 -> 16.624687 | K50: =K47-K49 -> 20.694345
B52: Taxes | D52: -0.8 | E52: -1 | F52: -0.7 | G52: -0.6 | H52: -0.6 | I52: =I50*I18 -> 1.1031215 | J52: =J50*J18 -> 2.4937031 | K52: =K50*K18 -> 3.3110952
B53: Net Income | D53: =D50-D52 -> -5.2 | E53: =E50-E52 -> -5.7 | F53: =F50-F52 -> -1.110223e-15 | G53: =G50-G52 -> -11 | H53: =H50-H52 -> 2 | I53: =I50-I52 -> 7.3824285 | J53: =J50-J52 -> 14.130984 | K53: =K50-K52 -> 17.38325
B55: Dividends | D55: 0 | E55: 0 | F55: 0 | G55: 0 | H55: =G55 -> 0 | I55: =H55 -> 0 | J55: =I55 -> 0 | K55: =J55 -> 0
B57: Balance Sheet
B59: All figures in USD Millions unless stated | D59: =D$7 -> 2021A | E59: =E$7 -> 2022A | F59: =F$7 -> 2023A | G59: =G$7 -> 2024A | H59: =H$7 -> 2025A | I59: =I$7 -> 2026E | J59: =J$7 -> 2027E | K59: =K$7 -> 2028E
B61: Assets
B62: Cash And Equivalents | D62: 5.3 | E62: 5.9 | F62: 2.2 | G62: 2.8 | H62: 4.3 | I62: =I138 -> 13.739428 | J62: =J138 -> 15.987742 | K62: =K138 -> 27.559031
B63: Short Term Investments | D63: 0 | E63: 0 | F63: 0 | G63: 0 | H63: 0 | I63: 0 | J63: 0 | K63: 0
B64: Trade and Other Receivables | D64: 2.3 | E64: 1.7 | F64: 3.3 | G64: 2.1 | H64: 50.8 | I64: =Assumptions!K45 -> 56 | J64: =Assumptions!L45 -> 67.39726 | K64: =Assumptions!M45 -> 71.441096
B65: Inventory | D65: 2.4 | E65: 2.4 | F65: 3.5 | G65: 8.1 | H65: 4.1 | I65: 5 | J65: 5 | K65: 5 | L65: flatline
B66: Prepaid Exp. | D66: 1.3 | E66: 3.1 | F66: 3.5 | G66: 1.1 | H66: 4.5 | I66: 4 | J66: 4 | K66: 4 | L66: flatline
B67: Restricted Cash | D67: 0 | E67: 0.9 | F67: 0.9 | G67: 0.9 | H67: 5.7 | I67: 0 | J67: 0 | K67: 0 | L67: lump into cash for modelling purposes
B68: Other Current Assets | D68: 0 | E68: 0 | F68: 0 | G68: 0 | H68: 0 | I68: 0 | J68: 0 | K68: 0
B69: Total Current Assets | D69: =SUM(D62:D68) -> 11.3 | E69: =SUM(E62:E68) -> 14 | F69: =SUM(F62:F68) -> 13.4 | G69: =SUM(G62:G68) -> 15 | H69: =SUM(H62:H68) -> 69.4 | I69: =SUM(I62:I68) -> 78.739428 | J69: =SUM(J62:J68) -> 92.385002 | K69: =SUM(K62:K68) -> 108.00013
B71: Gross Property, Plant & Equipment | D71: 3.7 | E71: 3.9 | F71: 4.3 | G71: 4.7 | H71: 5.4 | I71: =H71*1.02 -> 5.508 | J71: =I71*1.02 -> 5.61816 | K71: =J71*1.02 -> 5.7305232 | L71: p.a. 2% growth
B72: Accumulated Depreciation | D72: -2 | E72: -2.6 | F72: -3.1 | G72: -3.6 | H72: -4 | I72: -4 | J72: -4 | K72: -4 | L72: flatline
B73: Net Property, Plant & Equipment | D73: =D71+D72 -> 1.7 | E73: =E71+E72 -> 1.3 | F73: =F71+F72 -> 1.2 | G73: =G71+G72 -> 1.1 | H73: =H71+H72 -> 1.4 | I73: =I71+I72 -> 1.508 | J73: =J71+J72 -> 1.61816 | K73: =K71+K72 -> 1.7305232
B75: Investments and Long-Term Assets | D75: 9 | E75: 9.3 | F75: 11.7 | G75: 14.1 | H75: 16.7 | I75: =Assumptions!K52 -> 15.33 | J75: =Assumptions!L52 -> 15.375 | K75: =Assumptions!M52 -> 13.038
B76: Total Assets | D76: =D75 + D69 + D73 -> 22 | E76: =E75 + E69 + E73 -> 24.6 | F76: =F75 + F69 + F73 -> 26.3 | G76: =G75 + G69 + G73 -> 30.2 | H76: =H75 + H69 + H73 -> 87.5 | I76: =I75 + I69 + I73 -> 95.577428 | J76: =J75 + J69 + J73 -> 109.37816 | K76: =K75 + K69 + K73 -> 122.76865
B78: Liabilities
B79: Accounts Payable | D79: 1 | E79: 1.5 | F79: 2.5 | G79: 2.4 | H79: 5.2 | I79: =Assumptions!K58 -> 8.4 | J79: =Assumptions!L58 -> 10.109589 | K79: =Assumptions!M58 -> 10.716164
B80: Accrued Exp. | D80: 0.5 | E80: 4.8 | F80: 4.5 | G80: 1.3 | H80: 36.8 | I80: =I32*(H80/H32) -> 46.925102 | J80: =J32*(I80/I32) -> 54.383734 | K80: =K32*(J80/J32) -> 57.646758
B81: Curr. Port. of LT Debt | D81: 8.8 | E81: 7.4 | F81: 8.2 | G81: 10.9 | H81: 10.9 | I81: 10.9 | J81: 10.9 | K81: 10.9
B82: Def Tax Liability | D82: 0.1 | E82: 0.2 | F82: 0.2 | G82: 0 | H82: 1.2 | I82: 1.2 | J82: 1.2 | K82: 1.2
B83: Unearned Revenue, Curr | D83: 0 | E83: 0 | F83: 0 | G83: 0.1 | H83: 0.1 | I83: =(H83/H31)*I31 -> 0.13102564 | J83: =(I83/I31)*J31 -> 0.15769231 | K83: =(J83/J31)*K31 -> 0.16715385
B84: Total Current Liabilities | D84: =SUM(D79:D83) -> 10.4 | E84: =SUM(E79:E83) -> 13.9 | F84: =SUM(F79:F83) -> 15.4 | G84: =SUM(G79:G83) -> 14.7 | H84: =SUM(H79:H83) -> 54.2 | I84: =SUM(I79:I83) -> 67.556127 | J84: =SUM(J79:J83) -> 76.751015 | K84: =SUM(K79:K83) -> 80.630076
B86: Long-Term Debt | D86: 0 | E86: 0.3 | F86: 0 | G86: 3 | H86: 3 | I86: 3 | J86: 3 | K86: 3
B87: Other Non-Current Liabilities | D87: 0.9 | E87: 0.7 | F87: 0.6 | G87: 0.5 | H87: 0.4 | I87: 0.5 | J87: 0.5 | K87: 0.5
B88: Total Liabilities | D88: =D86+D84+D87 -> 11.3 | E88: =E86+E84+E87 -> 14.9 | F88: =F86+F84+F87 -> 16 | G88: =G86+G84+G87 -> 18.2 | H88: =H86+H84+H87 -> 57.6 | I88: =I86+I84+I87 -> 71.056127 | J88: =J86+J84+J87 -> 80.251015 | K88: =K86+K84+K87 -> 84.130076
B90: Equity
B91: Common Stock | D91: 0.2 | E91: 0.2 | F91: 0.2 | G91: 0.2 | H91: 0.3 | I91: 0.3 | J91: 0.3 | K91: 0.3
B92: Additional Paid In Capital | D92: 13.4 | E92: 18.1 | F92: 18.2 | G92: 33.2 | H92: 42.2 | I92: 42.2 | J92: 42.2 | K92: 42.2
B93: Comprehensive and Others | D93: 5.5 | E93: 5.5 | F93: 5.5 | G93: 5.5 | H93: 8.9 | I93: 8.9 | J93: 8.9 | K93: 8.9
B94: Retained Earnings | D94: -8.4 | E94: -13.9 | F94: -13.6 | G94: -26.8 | H94: -24.5 | I94: =H94+I53 -> -17.117571 | J94: =I94+J53 -> -2.9865871 | K94: =J94+K53 -> 14.396663
B95: Total Common Equity | D95: =SUM(D91:D94) -> 10.7 | E95: =SUM(E91:E94) -> 9.9 | F95: =SUM(F91:F94) -> 10.3 | G95: =SUM(G91:G94) -> 12.1 | H95: =SUM(H91:H94) -> 26.9 | I95: =SUM(I91:I94) -> 34.282429 | J95: =SUM(J91:J94) -> 48.413413 | K95: =SUM(K91:K94) -> 65.796663
B97: Total Liabilities And Equity | D97: =D95+D88 -> 22 | E97: =E95+E88 -> 24.8 | F97: =F95+F88 -> 26.3 | G97: =G95+G88 -> 30.3 | H97: =H95+H88 -> 84.5 | I97: =I95+I88 -> 105.33856 | J97: =J95+J88 -> 128.66443 | K97: =K95+K88 -> 149.92674
D98: =D97-D76 -> 0 | E98: =E97-E76 -> 0.2 | F98: =F97-F76 -> 0 | G98: =G97-G76 -> 0.1 | H98: =H97-H76 -> -3 | I98: =I97-I76 -> 9.7611273 | J98: =J97-J76 -> 19.286266 | K98: =K97-K76 -> 27.158089
B100: Cash Flow
B102: All figures in USD Millions unless stated | D102: =D$7 -> 2021A | E102: =E$7 -> 2022A | F102: =F$7 -> 2023A | G102: =G$7 -> 2024A | H102: =H$7 -> 2025A | I102: =I$7 -> 2026E | J102: =J$7 -> 2027E | K102: =K$7 -> 2028E
B104: Cash Flows from Operating Activities
B105: Net Income | D105: =D53 -> -5.2 | E105: =E53 -> -5.7 | F105: =F53 -> -1.110223e-15 | G105: =G53 -> -11 | H105: =H53 -> 2 | I105: =I53 -> 7.3824285 | J105: =J53 -> 14.130984 | K105: =K53 -> 17.38325
B106: Depreciation & Amort., Total | D106: 0.5 | E106: 0.5 | F106: 0.5 | G106: 0.4 | H106: 0.5 | I106: 0.5 | J106: 0.5 | K106: 0.5
B108: Other Amortization | D108: 2.3 | E108: 2.2 | F108: 2.4 | G108: 2.7 | H108: 2.7 | I108: =I37 -> 3 | J108: =J37 -> 3.3 | K108: =K37 -> 3.6
B109: Change in Acc. Receivable | D109: 12.4 | E109: -0.2 | F109: -2 | G109: 2.8 | H109: -51.1 | I109: =-I64+H64 -> -5.2 | J109: =-J64+I64 -> -11.39726 | K109: =-K64+J64 -> -4.0438356
B110: Change in Inventory | D110: -0.4 | E110: 0 | F110: -1.1 | G110: -3.7 | H110: 4 | I110: =-I65+H65 -> -0.9 | J110: =-J65+I65 -> 0 | K110: =-K65+J65 -> 0
B111: Stock Based Compensation | D111: 0.2 | E111: 0.3 | F111: 0.3 | G111: 0.3 | H111: 0.3 | I111: =-I66+H66 -> 0.5 | J111: =-J66+I66 -> 0 | K111: =-K66+J66 -> 0
B112: Change in Acc. Payable | D112: -7.4 | E112: 4.8 | F112: 0.6 | G112: -2.6 | H112: 38.3 | I112: =I79-H79 -> 3.2 | J112: =J79-I79 -> 1.709589 | K112: =K79-J79 -> 0.60657534
B113: Other Operating Activities | D113: 0.5 | E113: 0.4 | F113: 1 | G113: 0.9 | H113: 4.4 | I113: =-I68+H68 -> 0 | J113: =-J68+I68 -> 0 | K113: =-K68+J68 -> 0
B114: Cash flow from Operating Activities | D114: =SUM(D105:D113) -> 2.9 | E114: =SUM(E105:E113) -> 2.3 | F114: =SUM(F105:F113) -> 1.7 | G114: =SUM(G105:G113) -> -10.2 | H114: =SUM(H105:H113) -> 1.1 | I114: =SUM(I105:I113) -> 8.4824285 | J114: =SUM(J105:J113) -> 8.2433131 | K114: =SUM(K105:K113) -> 18.04599
B116: Investing Activities
B117: Capital Expenditure | D117: -0.3 | E117: -0.2 | F117: -0.2 | G117: -0.2 | H117: -0.5 | I117: =-Assumptions!K65*Assumptions!K10 -> -1.533 | J117: =-Assumptions!L65*Assumptions!L10 -> -1.845 | K117: =-Assumptions!M65*Assumptions!M10 -> -1.9557
B118: Purchase of Intangible Assets + Product Development | D118: -2.8 | E118: -3.3 | F118: -4.8 | G118: -4.6 | H118: -4.4 | I118: =-Assumptions!K70 -> -5.11 | J118: =-Assumptions!L70 -> -6.15 | K118: =-Assumptions!M70 -> -6.519
B119: Other Investing Activities | D119: 0 | E119: 0 | F119: 0 | G119: 0 | H119: 0.3 | I119: 0 | J119: 0 | K119: 0
B120: Cash flows from Investing Activities | D120: =SUM(D117:D119) -> -3.1 | E120: =SUM(E117:E119) -> -3.5 | F120: =SUM(F117:F119) -> -5 | G120: =SUM(G117:G119) -> -4.8 | H120: =SUM(H117:H119) -> -4.6 | I120: =SUM(I117:I119) -> -6.643 | J120: =SUM(J117:J119) -> -7.995 | K120: =SUM(K117:K119) -> -8.4747
B122: Financing Activities
B123: Total Debt Issued | D123: 3.5 | E123: 1 | F123: 1.7 | G123: 5.8 | H123: 22.9 | L123: Assumed business maintains short term financing strategy
B124: Total Debt Repaid | D124: -0.3 | E124: -2.2 | F124: -1.5 | G124: -1.5 | H124: -20.3
B125: Net Increase/(Decrease) in Debt | D125: =SUM(D123:D124) -> 3.2 | E125: =SUM(E123:E124) -> -1.2 | F125: =SUM(F123:F124) -> 0.2 | G125: =SUM(G123:G124) -> 4.3 | H125: =SUM(H123:H124) -> 2.6 | I125: 0 | J125: 0 | K125: 0
B127: Issuance of Common Stock | D127: 2 | E127: 4.9 | F127: 0.1 | G127: 12.8 | H127: 9.5 | I127: 0 | J127: 0 | K127: 0
B128: Repurchase of Common Stock | D128: 0 | E128: 0 | F128: 0 | G128: 0 | H128: 0 | I128: 0 | J128: 0 | K128: 0
B129: Net Increase/(Decrease) in Common Stock | D129: =SUM(D127:D128) -> 2 | E129: =SUM(E127:E128) -> 4.9 | F129: =SUM(F127:F128) -> 0.1 | G129: =SUM(G127:G128) -> 12.8 | H129: =SUM(H127:H128) -> 9.5 | I129: =I91-H91 -> 0 | J129: =J91-I91 -> 0 | K129: =K91-J91 -> 0
B131: Total Dividends Paid | D131: - | E131: - | F131: - | G131: - | H131: - | I131: - | J131: - | K131: -
B132: Other Financing Activities | D132: -0.6 | E132: -0.8 | F132: -0.7 | G132: -1.7 | H132: -2.4 | I132: 2 | J132: 2 | K132: 2 | L132: flatline
B133: Cash from Financing | D133: =D129+D125+D132 -> 4.6 | E133: =E129+E125+E132 -> 2.9 | F133: =F129+F125+F132 -> -0.4 | G133: =G129+G125+G132 -> 15.4 | H133: =H129+H125+H132 -> 9.7 | I133: =I129+I125+I132 -> 2 | J133: =J129+J125+J132 -> 2 | K133: =K129+K125+K132 -> 2
B136: Initial Cash Balance | H136: =G138 -> 3.7 | I136: =H138 -> 9.9 | J136: =I138 -> 13.739428 | K136: =J138 -> 15.987742
...

Sheet Sheet2

Sheet DCF
B2: Discounted Cash Flow Analysis
B3: $ in millions, unless otherwise noted | F3: =TODAY() -> 46071
B5: For Fiscal Year Ending | G5: 2025A | H5: 2026 | I5: =H5+1 -> 2027 | J5: =I5+1 -> 2028 | O5: Perpetuity Growth Method
B7: Total Revenues | G7: ='Three Statement Model'!H31 -> 78 | H7: ='Three Statement Model'!I31 -> 102.2 | I7: ='Three Statement Model'!J31 -> 123 | J7: ='Three Statement Model'!K31 -> 130.38 | O7: =$J$5&"E Unlevered Free Cash Flow" -> 2028E Unlevered Free Cash Flow | R7: =J29 -> 31.762989
B8: % growth | H8: =(H7-G7)/G7 -> 0.31025641 | I8: =(I7-H7)/H7 -> 0.2035225 | J8: =(J7-I7)/I7 -> 0.06 | O8: Perpetuity Growth Rate | R8: 0.02
O9: Terminal Value | R9: =(R7*(1+R8))/(D32-R8) -> 386.7555
B10: Cost of Goods Sold | G10: =-'Three Statement Model'!H32 -> 54.1 | H10: =-'Three Statement Model'!I32 -> 68.985 | I10: =-'Three Statement Model'!J32 -> 79.95 | J10: =-'Three Statement Model'!K32 -> 84.747 | O10: Discount Factor | R10: =J34 -> 0.74364393
B11: Gross Profit | G11: =G7-G10 -> 23.9 | H11: =H7-H10 -> 33.215 | I11: =I7-I10 -> 43.05 | J11: =J7-J10 -> 45.633 | O11: Present Value of Terminal Value | R11: =R10*R9 -> 287.60838
B12: % margin | G12: =G11/G7 -> 0.30641026 | H12: =H11/H7 -> 0.325 | I12: =I11/I7 -> 0.35 | J12: =J11/J7 -> 0.35 | O12: Present Value of Cash Flow | R12: =J37 -> 45.765537
O13: Total Enterprise Value | R13: =R12+R11 -> 333.37392
B14: SG&A Expense | G14: ='Three Statement Model'!H35 -> 14.8 | H14: ='Three Statement Model'!I35 -> 20.44 | I14: ='Three Statement Model'!J35 -> 21.525 | J14: ='Three Statement Model'!K35 -> 19.557 | O14: Less: Debt | R14: 17.2
B15: D&A Expense | G15: ='Three Statement Model'!H37 -> 2.7 | H15: ='Three Statement Model'!I37 -> 3 | I15: ='Three Statement Model'!J37 -> 3.3 | J15: ='Three Statement Model'!K37 -> 3.6 | O15: Plus: Cash | R15: 10
B16: Other Operating Expense | G16: ='Three Statement Model'!H36 -> 0 | H16: ='Three Statement Model'!I36 -> 0.6132 | I16: ='Three Statement Model'!J36 -> 0.738 | J16: ='Three Statement Model'!K36 -> 0.78228 | O16: Total Equity Value | R16: =R15-R14+R13 -> 326.17392
B17: EBIT | G17: =G11-SUM(G14:G16) -> 6.4 | H17: =H11-SUM(H14:H16) -> 9.1618 | I17: =I11-SUM(I14:I16) -> 17.487 | J17: =J11-SUM(J14:J16) -> 21.69372 | O17: Diluted Shares Outstanding | R17: 251.6
B18: % margin | G18: =G17/G7 -> 0.082051282 | H18: =H17/H7 -> 0.089645793 | I18: =I17/I7 -> 0.14217073 | J18: =J17/J7 -> 0.1663884 | O18: Implied Share Price | R18: =R16/R17 -> 1.2963987
O19: Upside | R19: =(R18-WACC!E10)/WACC!E10 -> 0.47318036
B20: Taxes | G20: ='Three Statement Model'!H52 -> -0.6 | H20: ='Three Statement Model'!I52 -> 1.1031215 | I20: ='Three Statement Model'!J52 -> 2.4937031 | J20: ='Three Statement Model'!K52 -> 3.3110952
B21: % effective tax rate | G21: =G20/G17 -> -0.09375 | H21: =H20/H17 -> 0.12040445 | I21: =I20/I17 -> 0.14260326 | J21: =J20/J17 -> 0.1526292
B22: Net Operating Profit After Tax | G22: =G17-G20 -> 7 | H22: =H17-H20 -> 8.0586785 | I22: =I17-I20 -> 14.993297 | J22: =J17-J20 -> 18.382625
B23: % margin | G23: =G22/G7 -> 0.08974359 | H23: =H22/H7 -> 0.07885204 | I23: =I22/I7 -> 0.12189672 | J23: =J22/J7 -> 0.14099267
B25: Plus: D&A Expense | G25: =G15 -> 2.7 | H25: =H15 -> 3 | I25: =I15 -> 3.3 | J25: =J15 -> 3.6
B26: Less: Capital Expenditures | G26: =-'Three Statement Model'!H117 -> 0.5 | H26: =-'Three Statement Model'!I117 -> 1.533 | I26: =-'Three Statement Model'!J117 -> 1.845 | J26: =-'Three Statement Model'!K117 -> 1.9557
B27: Less: Change in Net Working Capital | G27: =('Three Statement Model'!H69-'Three Statement Model'!H84) - ('Three Statement Model'!G69-'Three Statement Model'!G84) -> 14.9 | H27: =('Three Statement Model'!I69-'Three Statement Model'!I84) - ('Three Statement Model'!H69-'Three Statement Model'!H84) -> -4.0166988 | I27: =('Three Statement Model'!J69-'Three Statement Model'!J84) - ('Three Statement Model'!I69-'Three Statement Model'!I84) -> 4.4506855 | J27: =('Three Statement Model'!K69-'Three Statement Model'!K84) - ('Three Statement Model'!J69-'Three Statement Model'!J84) -> 11.736064
B28: Less: Stub Period
B29: Unlevered Free Cash Flow | G29: =G22+G25-G26-G27 -> -5.7 | H29: =H22+H25-H26+H27 -> 5.5089797 | I29: =I22+I25-I26+I27 -> 20.898982 | J29: =J22+J25-J26+J27 -> 31.762989
B30: % margin | G30: =G29/G7 -> -0.073076923 | H30: =H29/H7 -> 0.053903911 | I30: =I29/I7 -> 0.16991043 | J30: =J29/J7 -> 0.24361857
B32: WACC | D32: =WACC!$J$23 -> 0.10376933 | G32: =$D$32 -> 0.10376933 | H32: =$D$32 -> 0.10376933 | I32: =$D$32 -> 0.10376933 | J32: =$D$32 -> 0.10376933
B33: Discount Period | G33: 0 | H33: 1 | I33: 2 | J33: 3
B34: Discount Factor | G34: =1/(1+G32)^G33 -> 1 | H34: =1/(1+H32)^H33 -> 0.9059864 | I34: =1/(1+I32)^I33 -> 0.82081136 | J34: =1/(1+J32)^J33 -> 0.74364393
B35: Present Value of Unlevered Free Cash Flow | G35: =G29*G34 -> -5.7 | H35: =H29*H34 -> 4.9910607 | I35: =I29*I34 -> 17.154122 | J35: =J29*J34 -> 23.620354
B37: Sum of Present Value Cash Flows | J37: =SUM(H35:J35) -> 45.765537
B41: DCF Sensitivity Analysis: Upside / (Downside) - Perpetuity Growth Method
D42: Perpetuity Growth
C43: =R16/R17 -> 1.2963987 | D43: 0.0125 | E43: 0.015 | F43: 0.0175 | G43: 0.02 | H43: 0.0225 | I43: 0.025 | J43: 0.0275
B44: WACC | C44: 0.077 | D44: 1.7507311 | E44: 1.8187717 | F44: 1.8925299 | G44: 1.9727582 | H44: 2.0603469 | I44: 2.1563576 | J44: 2.2620663
C45: 0.082 | D45: 1.6141409 | E45: 1.6720353 | F45: 1.7344176 | G45: 1.8018308 | H45: 1.874909 | I45: 1.9543975 | J45: 2.0411785
C46: 0.087 | D46: 1.4959791 | E46: 1.5457761 | F46: 1.5991555 | G46: 1.6565186 | H46: 1.7183283 | I46: 1.7851228 | J46: 1.8575302
C47: =WACC!$J$23 -> 0.10376933 | D47: 1.1947492 | E47: 1.2267239 | F47: 1.2605517 | G47: 1.2963987 | H47: 1.3344511 | I47: 1.374919 | J47: 1.4180398
C48: 0.097 | D48: 1.30185 | E48: 1.3397001 | F48: 1.3799307 | G48: 1.4227736 | H48: 1.468492 | I48: 1.5173852 | J48: 1.5697959
C49: 0.102 | D49: 1.2211657 | E49: 1.2545425 | F49: 1.2898943 | G49: 1.3274017 | H49: 1.3672681 | I49: 1.4097232 | J49: 1.4550276
C50: 0.107 | D50: 1.1490888 | E50: 1.1787123 | F50: 1.2099907 | G50: 1.2430667 | H50: 1.2780999 | I50: 1.3152692 | J50: 1.3547763

Sheet WACC
B2: Weighted Average Cost of Capital
B3: £ in millions, unless otherwise noted
B5: Inputs | G5: Cost of Debt Calculation
B6: Risk-Free Rate | E6: 0.044
B7: Equity Risk Premium | E7: 0.06 | G7: Risk-Free Rate (10-Year Gilt) | J7: 0.044
B8: Beta* | E8: 1 | G8: Credit Spread on [XXX] Rating
B9: Effective Tax Rate | E9: =J10 -> 0.26 | G9: Pre-Tax Cost of Debt | J9: 8
B10: Current Share Price | E10: 0.88 | G10: Effective Tax Rate (UK Corp Tax 2025) | J10: 0.26
B11: Diluted Shares Outstanding | E11: 251600000 | G11: After-Tax Cost of Debt | J11: =J9*(1+J10)/100 -> 0.1008
B12: Market Value of Debt | E12: 17200000
G13: Cost of Equity Calculation
B14: *5Y Beta = 0.53; more conservative 1.0 used
G15: Risk-Free Rate | J15: =J7 -> 0.044
G16: Equity Risk Premium | J16: =E7 -> 0.06
E17: 16/11/2025 | G17: Beta | J17: =E8 -> 1
G18: Cost of Equity | J18: =J15+J16*J17 -> 0.104
B20: Weighted Average Cost of Capital Calculation | G20: Total Value | I20: % | J20: Cost
B21: Market Value of Debt | G21: =E12 -> 17200000 | I21: =G21/G23 -> 0.072084758 | J21: =J11 -> 0.1008
B22: Market Value of Equity | G22: =E10*E11 -> 221408000 | I22: =G22/G23 -> 0.92791524 | J22: =J18 -> 0.104
B23: Total | G23: =SUM(G21:G22) -> 238608000 | I23: =SUM(I21:I22) -> 1 | J23: =I21*J21+I22*J22 -> 0.10376933

Sheet Presentation Formatting
A1: WACC Calculation
F2: Perpetuity Growth Method
A3: Cost of Debt Calculation | F3: 2028E Unlevered Free Cash Flow | G3: 31.8
A4: Risk-Free Rate (10-Year Gilt) | D4: 0.044 | F4: Perpetuity Growth Rate | G4: 0.02
A5: Pre-Tax Cost of Debt | D5: 8 | F5: Terminal Value | G5: 386.8
A6: Effective Tax Rate (UK Corp Tax 2025) | D6: 0.26 | E6: *5Y Beta = 0.53; more conservative 1.0 used | F6: Discount Factor | G6: 0.74
A7: After-Tax Cost of Debt | D7: 0.1008 | F7: Present Value of Terminal Value | G7: 287.6
F8: Present Value of Cash Flow | G8: 45.8
A9: Cost of Equity Calculation | F9: Total Enterprise Value | G9: 333.4
A10: Risk-Free Rate | D10: 0.044 | F10: Less: Debt | G10: 17.2
A11: Equity Risk Premium | D11: 0.06 | F11: Plus: Cash | G11: 10
A12: Beta | D12: 1 | F12: Total Equity Value | G12: 326.2
A13: Cost of Equity | D13: 0.104 | F13: Diluted Shares Outstanding | G13: 251.6
F14: Implied Share Price | G14: £1.30
A15: WACC Calculation | B15: Total Value | C15: % | D15: Cost | F15: Upside | G15: 0.4732
A16: Market Value of Debt | B16: 17200000 | C16: 0.072084758 | D16: 0.1008
A17: Market Value of Equity | B17: 221408000 | C17: 0.92791524 | D17: 0.104
A18: Total | B18: 238608000 | C18: 1 | D18: 0.10376933
